[
    {"name":"南京","lon":118.79,"lat":32.06,"owm":"Nanjing,CN","qw":"101190101"},
    {"name":"溧水","lon":119.02,"lat":31.65,"owm":"Lishui,CN","qw":"101190103"},
    {"name":"高淳","lon":118.88,"lat":31.33,"owm":"Gaochun,CN","qw":"101190104"},
    {"name":"江宁","lon":118.84,"lat":31.95,"owm":"Jiangning,CN","qw":"101190102"},
    {"name":"六合","lon":118.83,"lat":32.36,"owm":"Liuhe,CN","qw":"101190105"},
    {"name":"浦口","lon":118.63,"lat":32.07,"owm":"Pukou,CN","qw":"101190107"},
    {"name":"上海","lon":121.47,"lat":31.23,"owm":"Shanghai,CN","qw":"101020100"},
    {"name":"浦东","lon":121.54,"lat":31.22,"owm":"Pudong,CN","qw":"101020600"},
    {"name":"宝山","lon":121.49,"lat":31.41,"owm":"Baoshan,CN","qw":"101020300"},
    {"name":"嘉定","lon":121.25,"lat":31.38,"owm":"Jiading,CN","qw":"101020500"},
    {"name":"松江","lon":121.23,"lat":31.03,"owm":"Songjiang,CN","qw":"101020700"},
    {"name":"杭州","lon":120.15,"lat":30.28,"owm":"Hangzhou,CN","qw":"101210101"},
    {"name":"宁波","lon":121.54,"lat":29.87,"owm":"Ningbo,CN","qw":"101210401"},
    {"name":"温州","lon":120.70,"lat":28.00,"owm":"Wenzhou,CN","qw":"101210701"},
    {"name":"嘉兴","lon":120.76,"lat":30.75,"owm":"Jiaxing,CN","qw":"101210301"},
    {"name":"湖州","lon":120.09,"lat":30.89,"owm":"Huzhou,CN","qw":"101210201"},
    {"name":"绍兴","lon":120.58,"lat":30.03,"owm":"Shaoxing,CN","qw":"101210501"},
    {"name":"金华","lon":119.65,"lat":29.08,"owm":"Jinhua,CN","qw":"101210901"},
    {"name":"衢州","lon":118.87,"lat":28.94,"owm":"Quzhou,CN","qw":"101211001"},
    {"name":"舟山","lon":122.21,"lat":29.99,"owm":"Zhoushan,CN","qw":"101211101"},
    {"name":"台州","lon":121.42,"lat":28.66,"owm":"Taizhou,CN","qw":"101210601"},
    {"name":"丽水","lon":119.92,"lat":28.47,"owm":"Lishui,CN","qw":"101210801"},
    {"name":"合肥","lon":117.23,"lat":31.86,"owm":"Hefei,CN","qw":"101220101"},
    {"name":"芜湖","lon":118.38,"lat":31.33,"owm":"Wuhu,CN","qw":"101220301"},
    {"name":"蚌埠","lon":117.36,"lat":32.92,"owm":"Bengbu,CN","qw":"101220201"},
    {"name":"安庆","lon":117.05,"lat":30.53,"owm":"Anqing,CN","qw":"101220601"},
    {"name":"马鞍山","lon":118.51,"lat":31.67,"owm":"Maanshan,CN","qw":"101220501"},
    {"name":"滁州","lon":118.31,"lat":32.30,"owm":"Chuzhou,CN","qw":"101221101"},
    {"name":"宣城","lon":118.75,"lat":30.94,"owm":"Xuancheng,CN","qw":"101221401"},
    {"name":"铜陵","lon":117.82,"lat":30.93,"owm":"Tongling,CN","qw":"101221301"},
    {"name":"池州","lon":117.49,"lat":30.66,"owm":"Chizhou,CN","qw":"101221701"},
    {"name":"黄山","lon":118.34,"lat":29.72,"owm":"Huangshan,CN","qw":"101221001"},
    {"name":"苏州","lon":120.59,"lat":31.30,"owm":"Suzhou,CN","qw":"101190401"},
    {"name":"无锡","lon":120.31,"lat":31.49,"owm":"Wuxi,CN","qw":"101190201"},
    {"name":"常州","lon":119.97,"lat":31.81,"owm":"Changzhou,CN","qw":"101191101"},
    {"name":"镇江","lon":119.43,"lat":32.19,"owm":"Zhenjiang,CN","qw":"101190301"},
    {"name":"南通","lon":120.89,"lat":31.98,"owm":"Nantong,CN","qw":"101190501"},
    {"name":"扬州","lon":119.42,"lat":32.39,"owm":"Yangzhou,CN","qw":"101190601"},
    {"name":"泰州","lon":119.92,"lat":32.46,"owm":"Taizhou,CN","qw":"101191201"},
    {"name":"盐城","lon":120.16,"lat":33.35,"owm":"Yancheng,CN","qw":"101190701"},
    {"name":"淮安","lon":119.02,"lat":33.61,"owm":"Huai'an,CN","qw":"101190901"},
    {"name":"徐州","lon":117.18,"lat":34.27,"owm":"Xuzhou,CN","qw":"101190801"},
    {"name":"连云港","lon":119.22,"lat":34.60,"owm":"Lianyungang,CN","qw":"101191001"},
    {"name":"宿迁","lon":118.28,"lat":33.96,"owm":"Suqian,CN","qw":"101191301"},
    {"name":"宿州","lon":116.98,"lat":33.63,"owm":"Suzhou,CN","qw":"101220701"},
    {"name":"阜阳","lon":115.81,"lat":32.89,"owm":"Fuyang,CN","qw":"101220801"},
    {"name":"亳州","lon":115.78,"lat":33.84,"owm":"Bozhou,CN","qw":"101220901"},
    {"name":"淮北","lon":116.79,"lat":33.97,"owm":"Huaibei,CN","qw":"101221201"},
    {"name":"淮南","lon":117.00,"lat":32.63,"owm":"Huainan,CN","qw":"101220401"},
    {"name":"六安","lon":116.50,"lat":31.73,"owm":"Lu'an,CN","qw":"101221501"},
    {"name":"义乌","lon":120.07,"lat":29.31,"owm":"Yiwu,CN","qw":"101210902"},
    {"name":"慈溪","lon":121.25,"lat":30.17,"owm":"Cixi,CN","qw":"101210403"},
    {"name":"昆山","lon":120.98,"lat":31.38,"owm":"Kunshan,CN","qw":"101190405"},
    {"name":"江阴","lon":120.27,"lat":31.91,"owm":"Jiangyin,CN","qw":"101190202"},
    {"name":"宜兴","lon":119.82,"lat":31.34,"owm":"Yixing,CN","qw":"101190203"},
    {"name":"张家港","lon":120.55,"lat":31.88,"owm":"Zhangjiagang,CN","qw":"101190403"},
    {"name":"常熟","lon":120.75,"lat":31.65,"owm":"Changshu,CN","qw":"101190402"},
    {"name":"太仓","lon":121.13,"lat":31.45,"owm":"Taicang,CN","qw":"101190404"},
    {"name":"丹阳","lon":119.57,"lat":32.00,"owm":"Danyang,CN","qw":"101190302"},
    {"name":"靖江","lon":120.28,"lat":32.01,"owm":"Jingjiang,CN","qw":"101191202"}
]
